py_ebooktools/__init__.py
py_ebooktools/convert_to_txt.py
py_ebooktools/edit.py
py_ebooktools/find_isbns.py
py_ebooktools/interactive_organizer.py
py_ebooktools/lib.py
py_ebooktools/organize_ebooks.py
py_ebooktools/rename_calibre_library.py
py_ebooktools/split_into_folders.py
py_ebooktools/configs/__init__.py
py_ebooktools/configs/default_config.py
py_ebooktools/configs/default_logging.py
py_ebooktools/scripts/__init__.py
py_ebooktools/scripts/ebooktools.py
py_ebooktools/utils/__init__.py
py_ebooktools/utils/genutils.py
py_ebooktools/utils/logutils.py
py_ebooktools-0.1.0a3.dist-info/LICENSE
py_ebooktools-0.1.0a3.dist-info/METADATA
py_ebooktools-0.1.0a3.dist-info/WHEEL
py_ebooktools-0.1.0a3.dist-info/entry_points.txt
py_ebooktools-0.1.0a3.dist-info/top_level.txt
py_ebooktools-0.1.0a3.dist-info/RECORD
