Metadata-Version: 2.1
Name: py-ebooktools
Version: 0.1.0a3
Summary: Program for organizing and managing ebook collections. It
Home-page: https://github.com/raul23/py-ebooktools
Author: Raul C.
Author-email: rchfe23@gmail.com
License: GPLv3
Project-URL: Bug Reports, https://github.com/raul23/py-ebooktools/issues
Project-URL: Source, https://github.com/raul23/py-ebooktools
Keywords: ebook-manager calibre script
Platform: UNKNOWN
Classifier: Development Status :: 3 - Alpha
Classifier: Environment :: Console
Classifier: Intended Audience :: Developers
Classifier: Intended Audience :: Other Audience
Classifier: License :: OSI Approved :: GNU General Public License v3 (GPLv3)
Classifier: Natural Language :: English
Classifier: Operating System :: MacOS
Classifier: Operating System :: POSIX :: Linux
Classifier: Programming Language :: Python :: 3
Classifier: Topic :: Software Development :: Libraries
Classifier: Topic :: Software Development :: Libraries :: Python Modules
Classifier: Topic :: Utilities
